rapl_formula/__init__.py
rapl_formula/__main__.py
rapl_formula/actor.py
rapl_formula/context.py
rapl_formula/dispatcher.py
rapl_formula-0.5.3.dist-info/LICENSE
rapl_formula-0.5.3.dist-info/METADATA
rapl_formula-0.5.3.dist-info/WHEEL
rapl_formula-0.5.3.dist-info/top_level.txt
rapl_formula-0.5.3.dist-info/RECORD
