Metadata-Version: 2.1
Name: rapl-formula
Version: 0.5.3
Summary: PowerAPI formula using RAPL counters to provides power consumption information.
Home-page: UNKNOWN
Author: Guillaume Fieni, Arthur d'Azémar, Jordan Bouchoucha, Romain Rouvoy
Author-email: powerapi-staff@inria.fr
License: BSD 3-Clause License
Keywords: energy,powerapi,power meter,rapl
Platform: any
Classifier: Programming Language :: Python :: 3.7
Classifier: License :: OSI Approved :: BSD License
Requires-Python: >=3.7
Requires-Dist: powerapi[influxdb,influxdb_client,mongodb,opentsdb,prometheus] (>=1.0.9)
Provides-Extra: docs
Requires-Dist: sphinx (>=1.8.1) ; extra == 'docs'
Provides-Extra: influxdb
Requires-Dist: influxdb (>=5.2.2) ; extra == 'influxdb'
Provides-Extra: mongodb
Requires-Dist: pymongo (>=3.7.2) ; extra == 'mongodb'
